niteco/__init__.py
niteco/agno_agent_tool/__init__.py
niteco/agno_agent_tool/agno_agent_tool_service.py
niteco_agno_agent_tool-0.1.1.dist-info/METADATA
niteco_agno_agent_tool-0.1.1.dist-info/WHEEL
niteco_agno_agent_tool-0.1.1.dist-info/top_level.txt
niteco_agno_agent_tool-0.1.1.dist-info/RECORD
