Metadata-Version: 2.4
Name: niteco.agno-agent-tool
Version: 0.1.1
Summary: A service that manages and executes agno agents with OPAL SDK integration
Home-page: https://github.com/niteco/agno-agent-tool
Author: Niteco
Author-email: Niteco <info@niteco.com>
Project-URL: Homepage, https://github.com/niteco/agno-agent-tool
Project-URL: Bug Reports, https://github.com/niteco/agno-agent-tool/issues
Project-URL: Source, https://github.com/niteco/agno-agent-tool
Classifier: Development Status :: 3 - Alpha
Classifier: Intended Audience :: Developers
Classifier: License :: OSI Approved :: MIT License
Classifier: Operating System :: OS Independent
Classifier: Programming Language :: Python :: 3
Classifier: Programming Language :: Python :: 3.8
Classifier: Programming Language :: Python :: 3.9
Classifier: Programming Language :: Python :: 3.10
Classifier: Programming Language :: Python :: 3.11
Classifier: Programming Language :: Python :: 3.12
Requires-Python: >=3.8
Requires-Dist: fastapi>=0.95.0
Requires-Dist: agno>=1.7.0
Requires-Dist: optimizely-opal.opal-tools-sdk>=0.1.0
Requires-Dist: pydantic>=2.0.0
Requires-Dist: uvicorn>=0.20.0
Provides-Extra: dev
Requires-Dist: pytest>=7.0; extra == "dev"
Requires-Dist: pytest-asyncio>=0.21.0; extra == "dev"
Requires-Dist: black>=22.0; extra == "dev"
Requires-Dist: isort>=5.0; extra == "dev"
Requires-Dist: mypy>=1.0; extra == "dev"
Dynamic: author
Dynamic: home-page
Dynamic: requires-python
